lumibot/__init__.py
lumibot/constants.py
lumibot/credentials.py
lumibot/backtesting/__init__.py
lumibot/backtesting/alpaca_backtesting.py
lumibot/backtesting/alpha_vantage_backtesting.py
lumibot/backtesting/backtesting_broker.py
lumibot/backtesting/ccxt_backtesting.py
lumibot/backtesting/databento_backtesting.py
lumibot/backtesting/databento_backtesting_pandas.py
lumibot/backtesting/databento_backtesting_polars.py
lumibot/backtesting/interactive_brokers_rest_backtesting.py
lumibot/backtesting/pandas_backtesting.py
lumibot/backtesting/polygon_backtesting.py
lumibot/backtesting/routed_backtesting.py
lumibot/backtesting/thetadata_backtesting.py
lumibot/backtesting/thetadata_backtesting_pandas.py
lumibot/backtesting/yahoo_backtesting.py
lumibot/brokers/__init__.py
lumibot/brokers/alpaca.py
lumibot/brokers/bitunix.py
lumibot/brokers/broker.py
lumibot/brokers/ccxt.py
lumibot/brokers/example_broker.py
lumibot/brokers/interactive_brokers.py
lumibot/brokers/interactive_brokers_rest.py
lumibot/brokers/projectx.py
lumibot/brokers/schwab.py
lumibot/brokers/tradier.py
lumibot/brokers/tradovate.py
lumibot/components/__init__.py
lumibot/components/configs_helper.py
lumibot/components/drift_rebalancer_logic.py
lumibot/components/grok_helper.py
lumibot/components/options_helper.py
lumibot/components/perplexity_helper.py
lumibot/components/quiver_helper.py
lumibot/components/vix_helper.py
lumibot/data_sources/__init__.py
lumibot/data_sources/alpaca_data.py
lumibot/data_sources/alpha_vantage_data.py
lumibot/data_sources/bitunix_data.py
lumibot/data_sources/ccxt_backtesting_data.py
lumibot/data_sources/ccxt_data.py
lumibot/data_sources/data_source.py
lumibot/data_sources/data_source_backtesting.py
lumibot/data_sources/databento_data.py
lumibot/data_sources/databento_data_pandas.py
lumibot/data_sources/databento_data_polars.py
lumibot/data_sources/example_broker_data.py
lumibot/data_sources/exceptions.py
lumibot/data_sources/interactive_brokers_data.py
lumibot-4.4.45.dist-info/licenses/LICENSE
lumibot-4.4.45.dist-info/METADATA
lumibot-4.4.45.dist-info/WHEEL
lumibot-4.4.45.dist-info/top_level.txt
lumibot-4.4.45.dist-info/RECORD
