Metadata-Version: 2.4
Name: lumibot
Version: 4.4.45
Summary: Backtesting and Trading Library, Made by Lumiwealth
Home-page: https://github.com/Lumiwealth/lumibot
Author: Robert Grzesik
Author-email: rob@lumiwealth.com
License: MIT
Classifier: Programming Language :: Python :: 3
Classifier: Operating System :: OS Independent
Requires-Python: >=3.10
License-File: LICENSE
Requires-Dist: polygon-api-client>=1.13.3
Requires-Dist: alpaca-py>=0.42.0
Requires-Dist: alpha_vantage
Requires-Dist: ibapi==9.81.1.post1
Requires-Dist: yfinance>=0.2.61
Requires-Dist: matplotlib>=3.3.3
Requires-Dist: quandl
Requires-Dist: numpy>=1.20.0
Requires-Dist: pandas>=2.2.0
Requires-Dist: polars>=1.32.3
Requires-Dist: pandas_market_calendars>=5.1.0
Requires-Dist: pandas-ta-classic>=0.3.14b0
Requires-Dist: plotly>=5.18.0
Requires-Dist: sqlalchemy
Requires-Dist: bcrypt
Requires-Dist: pytest
Requires-Dist: yappi>=1.6.0
Requires-Dist: scipy>=1.14.0
Requires-Dist: quantstats-lumi>=1.1.0
Requires-Dist: python-dotenv
Requires-Dist: ccxt>=4.4.80
Requires-Dist: termcolor
Requires-Dist: jsonpickle
Requires-Dist: apscheduler>=3.10.4
Requires-Dist: appdirs
Requires-Dist: pyarrow>=15.0.0
Requires-Dist: tqdm
Requires-Dist: lumiwealth-tradier>=0.1.18
Requires-Dist: pytz
Requires-Dist: psycopg2-binary
Requires-Dist: exchange_calendars>=4.6.0
Requires-Dist: duckdb
Requires-Dist: tabulate
Requires-Dist: databento>=0.42.0
Requires-Dist: holidays
Requires-Dist: psutil
Requires-Dist: openai
Requires-Dist: schwab-py>=1.5.0
Requires-Dist: Flask>=2.3
Requires-Dist: free-proxy
Requires-Dist: requests-oauthlib
Requires-Dist: boto3>=1.40.64
Provides-Extra: thetadata
Requires-Dist: thetadata; extra == "thetadata"
Dynamic: author
Dynamic: author-email
Dynamic: classifier
Dynamic: description
Dynamic: description-content-type
Dynamic: home-page
Dynamic: license
Dynamic: license-file
Dynamic: provides-extra
Dynamic: requires-dist
Dynamic: requires-python
Dynamic: summary
